MANIFEST.in
README.md
setup.cfg
setup.py
ricloud/__init__.py
ricloud/__main__.py
ricloud/cli.py
ricloud/compat.py
ricloud/conf.py
ricloud/exceptions.py
ricloud/requests.py
ricloud/ricloud.ini
ricloud/signing.py
ricloud/storage.py
ricloud/utils.py
ricloud/webhooks.py
ricloud.egg-info/PKG-INFO
ricloud.egg-info/SOURCES.txt
ricloud.egg-info/dependency_links.txt
ricloud.egg-info/entry_points.txt
ricloud.egg-info/not-zip-safe
ricloud.egg-info/requires.txt
ricloud.egg-info/top_level.txt
ricloud/resources/__init__.py
ricloud/resources/abase.py
ricloud/resources/configs.py
ricloud/resources/events.py
ricloud/resources/keys.py
ricloud/resources/organisation.py
ricloud/resources/permissions.py
ricloud/resources/polls.py
ricloud/resources/results.py
ricloud/resources/sessions.py
ricloud/resources/sources.py
ricloud/resources/subscriptions.py
ricloud/resources/tasks.py
ricloud/resources/users.py
ricloud/samples/__init__.py
ricloud/samples/helpers.py
ricloud/samples/icloud.py
ricloud/samples/rirelay.py
ricloud/samples/utils.py