Metadata-Version: 2.1
Name: ricloud
Version: 3.1.0
Summary: Python client for Reincubate's ricloud API.
Home-page: https://github.com/reincubate/ricloud
Author: Reincubate
Author-email: enterprise@reincubate.com
License: AGPLv3
Platform: UNKNOWN
Classifier: Development Status :: 5 - Production/Stable
Classifier: Environment :: Console
Classifier: Intended Audience :: Developers
Classifier: License :: OSI Approved :: GNU General Public License (GPL)
Classifier: Natural Language :: English
Classifier: Operating System :: OS Independent
Classifier: Programming Language :: Python :: 2.7
Classifier: Programming Language :: Python :: 3.4
Classifier: Programming Language :: Python :: 3.5
Classifier: Programming Language :: Python :: 3.6
Classifier: Programming Language :: Python :: 3.7
Classifier: Topic :: Utilities
Requires-Python: >=2.7, !=3.0.*, !=3.1.*, !=3.2.*, !=3.3.*
Provides-Extra: gs
Provides-Extra: s3
Provides-Extra: event
